wmh_seg/__init__.py
wmh_seg/model_loader.py
wmh_seg/test.py
wmh_seg/wmh_pytorch.py
wmh_seg-0.1.1.dist-info/METADATA
wmh_seg-0.1.1.dist-info/WHEEL
wmh_seg-0.1.1.dist-info/top_level.txt
wmh_seg-0.1.1.dist-info/RECORD
